jimit/__init__.py
jimit/check.py
jimit/common.py
jimit/convert.py
jimit/downloader.py
jimit/ji_exceptions.py
jimit/ji_time.py
jimit/keep_read.py
jimit/net_utils.py
jimit/regex.py
jimit/router.py
jimit/security.py
jimit/state_code.py
jimit/transaction_serial_number.py
jimit/orm/__init__.py
jimit/orm/filter.py
jimit/orm/orm.py
jimit/orm/orm_exceptions.py
jimit/terminal/__init__.py
jimit/terminal/color.py
jimit-3.9.6.dist-info/METADATA
jimit-3.9.6.dist-info/WHEEL
jimit-3.9.6.dist-info/top_level.txt
jimit-3.9.6.dist-info/RECORD
